tshistory_xl/ZTSHISTORY.xlam
tshistory_xl/__init__.py
tshistory_xl/api.py
tshistory_xl/blueprint.py
tshistory_xl/cli.py
tshistory_xl/codecs.py
tshistory_xl/error_handler.py
tshistory_xl/excel_connect.py
tshistory_xl/funcs.py
tshistory_xl/http_custom.py
tshistory_xl/http_xl.py
tshistory_xl/macros.py
tshistory_xl/testutil.py
tshistory_xl/tsio.py
tshistory_xl/zts-refinery.xlam
tshistory_xl-0.8.0.dist-info/METADATA
tshistory_xl-0.8.0.dist-info/WHEEL
tshistory_xl-0.8.0.dist-info/entry_points.txt
tshistory_xl-0.8.0.dist-info/top_level.txt
tshistory_xl-0.8.0.dist-info/RECORD
