Metadata-Version: 2.1
Name: tshistory_xl
Version: 0.8.0
Summary: Light client for excel/tshistory
Author: Pythonian
Author-email: arnaud.campeas@pythonian.fr, aurelien.campeas@pythonian.fr
Classifier: Development Status :: 4 - Beta
Classifier: Intended Audience :: Developers
Classifier: License :: OSI Approved :: GNU Lesser General Public License v3 (LGPLv3)
Classifier: Operating System :: OS Independent
Classifier: Programming Language :: Python :: 3
Classifier: Topic :: Database
Classifier: Topic :: Scientific/Engineering
Classifier: Topic :: Software Development :: Version Control
Requires-Dist: pandas <2.3,>1.0.5
Requires-Dist: colorlover
Requires-Dist: requests
Requires-Dist: python-dateutil
Requires-Dist: isodate
Requires-Dist: tshistory
Requires-Dist: tshistory-formula
Requires-Dist: tshistory-supervision
Provides-Extra: dev
Requires-Dist: rework ; extra == 'dev'
Requires-Dist: pytest ; extra == 'dev'
Requires-Dist: responses ; extra == 'dev'
Requires-Dist: webtest ; extra == 'dev'
Requires-Dist: pytest-sa-pg ; extra == 'dev'
